monitor_promdiscovery/__init__.py
monitor_promdiscovery/__main__.py
monitor_promdiscovery/hosts_by_hostgroup.py
monitor_promdiscovery/http_connection.py
monitor_promdiscovery/icinga2.py
monitor_promdiscovery/log.py
monitor_promdiscovery/main.py
monitor_promdiscovery/monitor.py
monitor_promdiscovery/prom.py
monitor_promdiscovery/system_factory.py
monitor_promdiscovery/system_request.py
monitor_promdiscovery-0.2.1.dist-info/COPYING
monitor_promdiscovery-0.2.1.dist-info/LICENSE
monitor_promdiscovery-0.2.1.dist-info/METADATA
monitor_promdiscovery-0.2.1.dist-info/WHEEL
monitor_promdiscovery-0.2.1.dist-info/top_level.txt
monitor_promdiscovery-0.2.1.dist-info/RECORD
